MANIFEST.in
setup.py
blackbird/__init__.py
blackbird/__init__.pyc
blackbird/sr71.py
blackbird.egg-info/PKG-INFO
blackbird.egg-info/SOURCES.txt
blackbird.egg-info/dependency_links.txt
blackbird.egg-info/entry_points.txt
blackbird.egg-info/requires.txt
blackbird.egg-info/top_level.txt
blackbird/plugins/__init__.py
blackbird/plugins/base.py
blackbird/plugins/netstat.py
blackbird/plugins/statistics.py
blackbird/plugins/zabbix_sender.py
blackbird/utils/__init__.py
blackbird/utils/argumentparse.py
blackbird/utils/base.py
blackbird/utils/configread.py
blackbird/utils/error.py
blackbird/utils/helpers.py
blackbird/utils/logger.py
scripts/blackbird-statistics.cfg
scripts/blackbird-zabbix_sender.cfg
scripts/blackbird.bin
scripts/blackbird.cfg
scripts/blackbird.init
scripts/blackbird.logrotate
scripts/blackbird.service
scripts/blackbird.spec
scripts/blackbird.sysconfig