Metadata-Version: 1.1
Name: blackbird
Version: 0.4.1
Summary: Daemon that monitor each middleware by using ZABBIX-SENDER
Home-page: https://github.com/Vagrants/blackbird
Author: ARASHI, Jumpei
Author-email: jumpei.arashi@arashike.com
License: WTFPL
Platform: UNKNOWN
Classifier: Programming Language :: Python :: 2.6
Classifier: Programming Language :: Python :: 2.7
